[
    {
        "Name": "rahul gandhi",
        "UserTag": "Rahul Gandhi",
        "Timestamp": "2024-06-04T13:10:22.000Z",
        "TweetContent": "भारत की जनता ने संविधान और लोकतंत्र को बचा लिया है।\n\nदेश की वंचित और गरीब आबादी अपने अधिकारों की रक्षा के लिए INDIA के साथ खड़ी हो गयी।\n\nगठबंधन के सभी साथियों और कांग्रेस के बब्बर शेर कार्यकर्ताओं को बधाई।",
        "Reply": "11K",
        "Retweet": "28K",
        "Like": "143K"
    },
    {
        "Name": "rahul gandhi",
        "UserTag": "Rahul Gandhi",
        "Timestamp": "2024-07-07T08:49:16.000Z",
        "TweetContent": "नरेंद्र मोदी की सरकार में लोको पायलट्स के जीवन की रेल पूरी तरह पटरी से उतर चुकी है।\n\nगर्मी से खौलते केबिन में बैठ कर लोको पायलट्स 16-16 घंटे काम करने को मजबूर हैं। \n\nजिनके भरोसे करोड़ों ज़िंदगियां चलती हैं, उनकी अपनी ज़िन्दगी का कोई भरोसा नहीं रह गया है।\n\nयूरिनल जैसी बेसिक",
        "Reply": "1.5K",
        "Retweet": "8.9K",
        "Like": "27K"
    },
    {
        "Name": "rahul gandhi",
        "UserTag": "Rahul Gandhi",
        "Timestamp": "2024-07-07T05:42:11.000Z",
        "TweetContent": "हाथरस में भगदड़ हादसे से प्रभावित पीड़ित परिवारों से मुलाकात कर, उनका दुख महसूस कर और समस्याएं जान कर उत्तर प्रदेश के माननीय मुख्यमंत्री योगी आदित्यनाथ जी को पत्र के माध्यम से उनसे अवगत कराया।\n\nमुख्यमंत्री जी से मुआवजे की राशि को बढ़ाकर शोकाकुल परिवारों को जल्द से जल्द प्रदान",
        "Reply": "1.1K",
        "Retweet": "6.5K",
        "Like": "21K"
    },
    {
        "Name": "rahul gandhi",
        "UserTag": "Rahul Gandhi",
        "Timestamp": "2024-07-07T04:43:39.000Z",
        "TweetContent": "श्रद्धा और भक्ति के पर्व महाप्रभु श्री जगन्नाथ रथ यात्रा के अवसर पर सभी देशवासियों को हार्दिक बधाई एवं शुभकामनाएं। \n\nयह उत्सव आप सभी के जीवन में सुख, समृद्धि और शांति लाए।",
        "Reply": "1K",
        "Retweet": "3.9K",
        "Like": "19K"
    },
    {
        "Name": "rahul gandhi",
        "UserTag": "Rahul Gandhi",
        "Timestamp": "2024-07-06T15:31:25.000Z",
        "TweetContent": "The flood situation in Assam is becoming increasingly dangerous. My thoughts are with our brothers and sisters reeling under the deluge.\n\nDeepest condolences to the bereaved families. I appeal to Congress leaders and workers to provide help in rescue and rehabilitation",
        "Reply": "683",
        "Retweet": "6.2K",
        "Like": "22K"
    },
    {
        "Name": "rahul gandhi",
        "UserTag": "Rahul Gandhi",
        "Timestamp": "2024-07-06T14:08:35.000Z",
        "TweetContent": "कांग्रेस गुजरात के चुनाव में पूरी शक्ति और निडरता के साथ लड़ेगी और जीतेगी।\n\nहमारा हर एक कार्यकर्ता बब्बर शेर है, जो हमारे पार्टी के चिन्ह, अभय मुद्रा से प्रेरणा लेता है - डरो मत, डराओ मत।\n\nभाजपा और संघ परिवार के नेता नफ़रत और हिंसा फैलाने की कोशिश करते हैं, मगर INDIA ने जैसे",
        "Reply": "1.8K",
        "Retweet": "7.6K",
        "Like": "26K"
    },
    {
        "Name": "rahul gandhi",
        "UserTag": "Rahul Gandhi",
        "Timestamp": "2024-07-02T08:22:30.000Z",
        "TweetContent": "Unhindered, unfiltered, undaunted - a free and fair conversation is the strength of our democracy!\n\nI am here to speak with you, listen to you, and facilitate the true expression of the idea of India.\n\nFor all Communication related enquiries, including:\n\n- Media interviews\n-",
        "Reply": "1.4K",
        "Retweet": "8.9K",
        "Like": "32K"
    },
    {
        "Name": "rahul gandhi",
        "UserTag": "Rahul Gandhi",
        "Timestamp": "2024-07-01T17:22:44.000Z",
        "TweetContent": "हर धर्म सिखाता है - डरो मत, डराओ मत।\n\nसत्य के साथ खड़ा होना चाहिए, उससे पीछे नहीं हटना चाहिए, और अहिंसा के रास्ते पर चलना चाहिए।\n\nजब भाजपा ने देश में भय फैलाया, संविधान और लोकतंत्र की रक्षा के लिए INDIA ने इसी सोच को अपनाया।",
        "Reply": "9.5K",
        "Retweet": "22K",
        "Like": "83K"
    },
    {
        "Name": "rahul gandhi",
        "UserTag": "Rahul Gandhi",
        "Timestamp": "2024-07-01T15:40:42.000Z",
        "TweetContent": "पिछले 10 वर्षों में अल्पसंख्यकों पर अन्याय बहुत तेज़ी से बढ़े हैं।\n\nभाजपा ने मुसलमानों के विरुद्ध हिंसा और अत्याचार किया है, सिखों और क्रिश्चन्स के खिलाफ नफ़रत फैलाई है - हर अल्पसंख्यक वर्ग पर आक्रमण किया है।\n\nअल्पसंख्यक हर क्षेत्र में हिंदुस्तान का प्रतिनिधित्व करते हैं, नाम",
        "Reply": "4.9K",
        "Retweet": "15K",
        "Like": "49K"
    },
    {
        "Name": "rahul gandhi",
        "UserTag": "Rahul Gandhi",
        "Timestamp": "2024-07-01T13:57:07.000Z",
        "TweetContent": "हिंदुस्तान डर का देश नहीं है।\n\nहमारे सभी महापुरुषों ने अहिंसा की बात की, डर मिटाने की बात की।\n\nनरेंद्र मोदी, भाजपा और RSS पूरा हिंदू समाज नहीं हैं- जो हिंसा और नफ़रत फैलाता है, वो हिंदू हो ही नहीं सकता।",
        "Reply": "5K",
        "Retweet": "20K",
        "Like": "67K"
    },
    {
        "Name": "rahul gandhi",
        "UserTag": "Rahul Gandhi",
        "Timestamp": "2024-07-01T13:26:17.000Z",
        "TweetContent": "नरेंद्र मोदी 10 वर्षों से ‘भय का राज’ चला रहे हैं! \n\nसभी एजेंसियों, संस्थाओं और मीडिया पर कब्ज़ा कर समाज के हर वर्ग में भाजपा ने सिर्फ डर फैलाने का काम किया है। \n\n- किसानों को काले कानूनों का डर\n- स्टूडेंट्स को पेपर लीक का डर \n- युवाओं को बेरोज़गारी का डर\n- छोटे व्यापारियों को",
        "Reply": "3.4K",
        "Retweet": "18K",
        "Like": "58K"
    },
    {
        "Name": "rahul gandhi",
        "UserTag": "Rahul Gandhi",
        "Timestamp": "2024-07-01T08:43:53.000Z",
        "TweetContent": "LIVE: Motion of Thanks | 18th Lok Sabha",
        "Reply": "1.6K",
        "Retweet": "7.1K",
        "Like": "20K"
    },
    {
        "Name": "rahul gandhi",
        "UserTag": "Rahul Gandhi",
        "Timestamp": "2024-07-01T05:04:17.000Z",
        "TweetContent": "जन्मदिन की हार्दिक शुभकामनाएं, \n@yadavakhilesh\n भाई!\n\nआप स्वस्थ रहें, खुशहाल रहें और PDA की आवाज़ बुलंद करते रहें।",
        "Reply": "1.8K",
        "Retweet": "10K",
        "Like": "66K"
    },
    {
        "Name": "rahul gandhi",
        "UserTag": "Rahul Gandhi",
        "Timestamp": "2024-06-29T19:24:42.000Z",
        "TweetContent": "Congratulations Virat on an outstanding T20 career. You truly are signing off in grand style!",
        "Reply": "2.1K",
        "Retweet": "33K",
        "Like": "330K"
    },
    {
        "Name": "rahul gandhi",
        "UserTag": "Rahul Gandhi",
        "Timestamp": "2024-06-29T18:31:09.000Z",
        "TweetContent": "Congratulations to Team India on a spectacular World Cup Victory and a phenomenal performance throughout the tournament! \n\nSurya, what a brilliant catch! Rohit, this win is a testament to your leadership. Rahul, I know team India will miss your guidance. \n\nThe spectacular Men in",
        "Reply": "2.7K",
        "Retweet": "25K",
        "Like": "175K"
    },
    {
        "Name": "rahul gandhi",
        "UserTag": "Rahul Gandhi",
        "Timestamp": "2024-06-29T07:55:25.000Z",
        "TweetContent": "लद्दाख में टैंक के नदी पार करने के सैन्य अभ्यास के दौरान हुए हादसे में भारतीय सेना के पांच जवानों की शहादत का समाचार अत्यंत दुखद है। \n\nसभी शहीद जवानों को विनम्र श्रद्धांजलि अर्पित करते हुए शोक संतप्त परिजनों के प्रति गहरी संवेदनाएं व्यक्त करता हूं। दुख की इस घड़ी में हम उनके साथ",
        "Reply": "1K",
        "Retweet": "8.4K",
        "Like": "34K"
    },
    {
        "Name": "rahul gandhi",
        "UserTag": "Rahul Gandhi",
        "Timestamp": "2024-06-28T15:14:00.000Z",
        "TweetContent": "झारखंड के पूर्व मुख्यमंत्री हेमंत सोरेन जी की गिरफ्तारी बदले और राजनीतिक दुर्भावना से की गई थी।\n\nउच्च न्यायालय द्वारा उन्हें जमानत देने के फैसले का हम स्वागत करते हैं - सोरेन जी से फोन पर बात कर अपनी खुशी ज़ाहिर की।\n\nजो संविधान की रक्षा की भावना ले कर चलते हैं, सत्य खुद उनकी",
        "Reply": "1.5K",
        "Retweet": "10K",
        "Like": "43K"
    },
    {
        "Name": "rahul gandhi",
        "UserTag": "Rahul Gandhi",
        "Timestamp": "2024-06-28T10:17:00.000Z",
        "TweetContent": "The INDIA Opposition bloc wants to have a constructive debate with the Government on the NEET exam and the prevailing paper leak issue. \n\nIt is unfortunate that we weren’t allowed to do so in Parliament today. This is a serious concern that is causing anxiety to lakhs of families",
        "Reply": "2.3K",
        "Retweet": "17K",
        "Like": "57K"
    },
    {
        "Name": "rahul gandhi",
        "UserTag": "Rahul Gandhi",
        "Timestamp": "2024-06-26T06:05:08.000Z",
        "TweetContent": "LIVE: Welcoming the Speaker of the 18th Lok Sabha",
        "Reply": "693",
        "Retweet": "4.9K",
        "Like": "15K"
    },
    {
        "Name": "rahul gandhi",
        "UserTag": "Rahul Gandhi",
        "Timestamp": "2024-06-25T11:24:27.000Z",
        "TweetContent": "To protect the Constitution is the duty of every patriotic Indian. \n\nWe will fulfill this duty in full measure.",
        "Reply": "3.7K",
        "Retweet": "14K",
        "Like": "67K"
    },
    {
        "Name": "rahul gandhi",
        "UserTag": "Rahul Gandhi",
        "Timestamp": "2024-06-25T10:40:59.000Z",
        "TweetContent": "LIVE: Taking Oath as Member of Parliament, 18th Lok Sabha",
        "Reply": "917",
        "Retweet": "4.6K",
        "Like": "14K"
    },
    {
        "Name": "rahul gandhi",
        "UserTag": "Rahul Gandhi",
        "Timestamp": "2024-06-24T10:24:13.000Z",
        "TweetContent": "हाथों में संविधान की प्रति, दिलों में इसके मूल्य!\n\nदुनिया की कोई शक्ति इसे मिटा नहीं सकती - INDIA जी जान से इसकी रक्षा करेगा।",
        "Reply": "3.6K",
        "Retweet": "12K",
        "Like": "48K"
    },
    {
        "Name": "rahul gandhi",
        "UserTag": "Rahul Gandhi",
        "Timestamp": "2024-06-24T07:54:38.000Z",
        "TweetContent": "NDA के पहले 15 दिन! \n\n1. भीषण ट्रेन दुर्घटना\n2. कश्मीर में आतंकवादी हमले\n3. ट्रेनों में यात्रियों की दुर्दशा\n4. NEET घोटाला\n5. NEET PG निरस्त\n6. UGC NET का पेपर लीक\n7. दूध, दाल, गैस, टोल और महंगे\n8. आग से धधकते जंगल\n9. जल संकट\n10. हीट वेव में इंतजाम न होने से मौतें",
        "Reply": "7.3K",
        "Retweet": "19K",
        "Like": "66K"
    },
    {
        "Name": "rahul gandhi",
        "UserTag": "Rahul Gandhi",
        "Timestamp": "2024-06-22T17:44:28.000Z",
        "TweetContent": "अब NEET PG भी स्थगित! \n\nयह नरेंद्र मोदी के राज में बर्बाद हो चुकी शिक्षा व्यवस्था का एक और दुर्भाग्यपूर्ण उदाहरण है।\n\nभाजपा राज में छात्र अपना करियर बनाने के लिए ‘पढ़ाई’ नहीं, अपना भविष्य बचाने के लिए सरकार से ‘लड़ाई’ लड़ने को मजबूर है।\n\nअब यह स्पष्ट है - हर बार चुप-चाप तमाशा",
        "Reply": "2.1K",
        "Retweet": "14K",
        "Like": "49K"
    },
    {
        "Name": "rahul gandhi",
        "UserTag": "Rahul Gandhi",
        "Timestamp": "2024-06-22T06:43:38.000Z",
        "TweetContent": "तेलंगाना के किसान परिवारों को बधाई! \n\nकांग्रेस सरकार ने आपके 2 लाख रू तक के सभी ऋण माफ कर ‘किसान न्याय’ के संकल्प को पूरा करने की दिशा में ऐतिहासिक कदम बढ़ाया है - जो 40 लाख से ज़्यादा किसान परिवारों को कर्ज़ मुक्त बनाएगा।\n\nजो कहा, कर के दिखाया - यही नियत है और आदत भी।\n\nकांग्रेस",
        "Reply": "2K",
        "Retweet": "11K",
        "Like": "43K"
    },
    {
        "Name": "rahul gandhi",
        "UserTag": "Rahul Gandhi",
        "Timestamp": "2024-06-21T14:18:23.000Z",
        "TweetContent": "NEET देने वाले हज़ारों स्टूडेंट्स अपने परिवारों के साथ भयंकर गर्मी में सड़क पर हैं और नरेंद्र मोदी चुप-चाप तमाशा देख रहे हैं।\n\nउन्हें भरोसा दिलाता हूं कि इस संघर्ष में सड़क से लेकर संसद तक INDIA आपके साथ है।\n\nपरीक्षार्थियों से चर्चा का पूरा वीडियो देखें:",
        "Reply": "1.8K",
        "Retweet": "16K",
        "Like": "53K"
    },
    {
        "Name": "rahul gandhi",
        "UserTag": "Rahul Gandhi",
        "Timestamp": "2024-06-20T13:26:57.000Z",
        "TweetContent": "एक और महत्वपूर्ण बात जो प्रेस कॉन्फ्रेंस में कहनी रह गई।\n\nनरेंद्र मोदी और उनके काफिले पर चप्पल फेंका जाना बहुत ही निंदनीय है और उनकी सुरक्षा में गंभीर चूक है।\n\nसरकार की नीतियों पर अपना विरोध गांधीवादी तरीके से दर्ज कराया जाना चाहिए, लोकतंत्र में हिंसा और नफ़रत की कोई जगह नहीं है।",
        "Reply": "2.7K",
        "Retweet": "15K",
        "Like": "61K"
    },
    {
        "Name": "rahul gandhi",
        "UserTag": "Rahul Gandhi",
        "Timestamp": "2024-06-20T12:09:47.000Z",
        "TweetContent": "हिंदुस्तान में लगातार पेपर लीक हो रहे हैं और नरेंद्र मोदी या तो उसे रोक नहीं पा रहे या रोकना ही नहीं चाहते।\n\nभाजपा शासित राज्य पेपर लीक का एपिसेंटर और शिक्षा माफियाओं की लैबोरेटरी बन गए हैं।\n\nभाजपा सरकार शिक्षा व्यवस्था को चौपट कर युवाओं के भविष्य से खिलवाड़ कर रही है।\n\n INDIA",
        "Reply": "1.3K",
        "Retweet": "11K",
        "Like": "35K"
    },
    {
        "Name": "rahul gandhi",
        "UserTag": "Rahul Gandhi",
        "Timestamp": "2024-06-20T09:49:40.000Z",
        "TweetContent": "LIVE: Press Conference | AICC HQ, New Delhi",
        "Reply": "634",
        "Retweet": "4.6K",
        "Like": "13K"
    },
    {
        "Name": "rahul gandhi",
        "UserTag": "Rahul Gandhi",
        "Timestamp": "2024-06-19T15:28:34.000Z",
        "TweetContent": "जन्मदिन की शुभकामनाओं के लिए आप सभी का दिल से धन्यवाद। \n\nमुझसे अक्सर पूछा जाता है कि मैं हमेशा 'सफेद T-shirt' क्यों पहनता हूं - यह T-shirt मेरे लिए पारदर्शिता, दृढ़ता और सरलता का प्रतीक है। \n\nआपके जीवन में ये मूल्य कहां और कितनी उपयोगी हैं ये #WhiteTshirtArmy इस्तेमाल कर मुझे एक",
        "Reply": "4.8K",
        "Retweet": "13K",
        "Like": "59K"
    }
]